tests/__init__.py
tests/test_whatsparser.py
whatsparser/__init__.py
whatsparser/whatsparser.py
WhatsParser-0.6.0.dist-info/LICENSE
WhatsParser-0.6.0.dist-info/METADATA
WhatsParser-0.6.0.dist-info/WHEEL
WhatsParser-0.6.0.dist-info/top_level.txt
WhatsParser-0.6.0.dist-info/RECORD
