Metadata-Version: 2.1
Name: WhatsParser
Version: 0.6.0
Summary: A parser for whatsapp .txt files
Home-page: https://github.com/nonsignificantp/whatsparser
Author: Agustin Rodriguez
Author-email: agustin.dev@protonmail.com
License: MIT
Keywords: whatsapp,parser,text,dataframe
Platform: UNKNOWN
Classifier: Programming Language :: Python :: 3
Classifier: License :: OSI Approved :: MIT License
Classifier: Operating System :: OS Independent
